pyutils/__init__.py
pyutils/eventlogger.py
pyutils/filequeue.py
pyutils/multilevelformatter.py
pyutils/throttledclientsession.py
tests/__init__.py
tests/test_dvplc.py
dvplc-0.1.2.dist-info/LICENSE
dvplc-0.1.2.dist-info/METADATA
dvplc-0.1.2.dist-info/WHEEL
dvplc-0.1.2.dist-info/entry_points.txt
dvplc-0.1.2.dist-info/top_level.txt
dvplc-0.1.2.dist-info/RECORD
