Metadata-Version: 2.1
Name: dvplc
Version: 0.1.2
Summary: CLI app to convert Dava SmartDLC .dvpl files used in Wargaming.net's World of Tanks Bliz MMO game
Author-email: Jylpah <Jylpah@gmail.com>
License: MIT License
Project-URL: Homepage, https://github.com/Jylpah/dvplc
Classifier: Programming Language :: Python :: 3
Classifier: License :: OSI Approved :: MIT License
Classifier: Operating System :: OS Independent
Requires-Python: >=3.10
License-File: LICENSE
Requires-Dist: lz4
Requires-Dist: aiofiles
Requires-Dist: aioconsole
Requires-Dist: importlib-metadata
